{
  "project_info": {
    "project_number": "609672071595",
    "project_id": "assist4web-app",
    "storage_bucket": "assist4web-app.firebasestorage.app"
  },
  "client": [
    {
      "client_info": {
        "mobilesdk_app_id": "1:609672071595:android:5247c621fa19406ea76aee",
        "android_client_info": {
          "package_name": "com.assist4webapp"
        }
      },
      "oauth_client": [],
      "api_key": [
        {
          "current_key": "AIzaSyCr7_2942Eq9ToMsuDiKJ8fuTAVofBLl1U"
        }
      ],
      "services": {
        "appinvite_service": {
          "other_platform_oauth_client": []
        }
      }
    }
  ],
  "configuration_version": "1"
}